{
  "id": "in-love-with-you",
  "slug": "in-love-with-you",
  "title": "In Love With you",
  "description": "In Love With you melody reference imported from an authorized runtime detail page and normalized into the current lightweight ocarina-tab renderer.",
  "published": false,
  "alignedLyrics": [
    "Just a gen tle whis per _ told me that _ _ you'd gone _ Leav ing on ly me mo ries",
    "where did we _ go _ wrong _ I couldn't _ find the _ words then so let me say _ them now _ I'm still _ in love _ with you",
    "_",
    "Tell me that you _ love _ me tell me that _ you care Tell me that you _ need me and",
    "I'll be _ there _ I'll be _ there wait ing _",
    "I will al ways love you _ _ I will al ways stay _ _ true There's no one who loves you like _ I _ do _ Come to me _ now",
    "I will ne ver leave _ you I will stay here with _ you Through the good _ and bad I _ will _ stand _ true I'm in",
    "love with you",
    "Now _ we're here _ toge ther yes ter day _ has _ past _",
    "Life is just begin _ _ ning close to you _ at _ last _ And I pro mise to _ you I will al _ ways be there _",
    "I give _ my all to you _",
    "Li ving life with _ out you _ is more than I _ can bear _ _ _ _",
    "Hold me close for e ver _ _ _ I'll be _ there for you I will al ways love you _ _",
    "I will al ways stay _ _ true There's no one _ who loves _ you _ like _ _ I do _ This I pro _ mise. I will ne ver leave _ you",
    "I will stay here with _ _ you Through the good _ and bad I _ will _ stand _ true Hold me _ clo _ ser Our love is for e ver",
    "Hold ing us to ge _ ther _ No thing in _ this world can _ stop _ us _ now Love _ has found a",
    "way _ _ _ _ _ _ _ _ _ _",
    "",
    "I'm in love _",
    "_ _ _ _ _ Yes, I'm _ in love _ _ _ _ _ _ _ _ _ _ _ _ I _ in love _",
    "_ _ _ _ _ _ with you _ _"
  ],
  "source": {
    "title": "Authorized runtime detail snapshot",
    "url": "https://www.kuaiyuepu.com/jianpu/q6Ohk129F.html",
    "rights": "Prepared from authorized runtime material for notation review. Publish only after rights review.",
    "note": "Raw context captured from authorized runtime song q6Ohk129F on 2026-05-23."
  },
  "meta": {
    "key": "1 = bE",
    "tempo": 100,
    "meter": "4/4"
  },
  "review": {
    "status": "pending",
    "checkedOn": "2026-05-23",
    "note": "Authorized runtime live compare and doctor checks passed on 2026-05-23. Keep unpublished in the local grey-song stock pool until publish approval, then promote with manifest, SEO, learn/hub links, and rollout drafts."
  },
  "tonicMidi": 63,
  "notation": [
    "0 0 0 0 0 0 1 - - 7, - - 1 - - - - - 2 - - - - - 1 - - - - - - - - 5, - - 5, - - - - - - - - - - - | 1 - - - - - 1 - - 1 - - 1 - - 2 - - 3 - - 3 - - 3 - - - - - - - - - - - | 0 0 0 0 0 0 1 - - 7, - - 1 - - - - - 2 - - - - - 1 - - - - - - - - 5, - - 5, - - - - - - - - - - - |",
    "4 - - - - - 4 - - 3 - - 3 - - 1 - - 2 - - 2 - - 2 - - - - - - - - - - - 0 0 0 0 0 0 0 0 0 0 0 0 | 0 0 0 5, - - 1 - - 7, - - 1 - - - - - 2 - - 1 - - 1 - - - - - 5, - - - - - - - - - - - 0 0 0 5, - - | 1 - - - - - 7, - - 1 - - 1 - - 3 - - - - - 3 - - 3 - - - - - - - - - - - 0 0 0 0 0 0 0 0 0 0 0 0 | 4 - - - - - - - - 3 - - 3 - - - - - 1 - - - - - 1 - - - - - 1 - - - - - 7, - - - - - 1 - - - - - |",
    "1 - - - - - - - - - - - - - - - - - - - - - - - 0 0 0 0 0 0 0 0 0 0 0 0 0 0 0 0 0 0 0 0 0 0 0 0 |",
    "0 0 0 0 0 0 1 - - 7, - - 1 - - - - - 2 - - 1 - - 1 - - - - - - - - 5, - - 5, - - - - - - - - - - - | 4, - - - - - 3, - - 4, - - 4, - - 5, - - - - - - - - 5, - - - - - - - - - - - - - - - - - - - - - - - | 0 0 0 0 0 0 1 - - 7, - - 1 - - - - - 2 - - 1 - - 1 - - - - - - - - - - - 5, - - 0 0 0 1 - - - - - |",
    "4 - - - - - - - - 3 - - 3 - - - - - 1 - - - - - 1 - - - - - - - - - - - - - - - - - - - - - - - | 4 - - - - - - - - 3 - - 1 - - - - - 1 - - - - - 1 - - - - - - - - - - - | 2 - - - - - - - - - - - - - - - - - - - - - - - - - - - - - - - - - - - - - - - - - - - - - - - | 2 - - - - - - - - - - - - - - - - - - - - - - - - - - - - - - - - - - - 0 0 0 0 0 0 0 0 0 0 0 0 |",
    "3 - - - - - 3 - - - - - 3 - - - - - 5 - - - - - 4 - - - - - - - - - - - 3 - - - - - 2 - - 1 - - | 2 - - - - - 2 - - - - - 2 - - - - - 4 - - - - - 3 - - 4 - - 3 - - - - - 2 - - - - - 0 0 0 0 0 0 | 1 - - - - - 7, - - - - - 1 - - - - - 2 - - - - - 3 - - - - - 2 - - 1 - - 7, - - - - - 7, - - 6, - - | 7, - - 6, - - 0 0 0 0 0 0 6, - - - - - 7, - - - - - 1 - - - - - - - - 2 - - 2 - - - - - - - - - - - |",
    "1 - - - - - 1 - - - - - 1 - - - - - 3 - - - - - 2 - - - - - - - - 1 - - 1 - - - - - - - - - - - | 7, - - - - - 7, - - - - - 7, - - - - - 2 - - - - - 1 - - - - - 7, - - - - - 7, - - - - - - - - - - - | 6, - - - - - 6, - - 6, - - 6, - - - - - 7, - - - - - 1 - - - - - 7, - - 6, - - 6, - - 5, - - 5, - - 6, - - | 6, - - - - - - - - - - - - - - - - - - - - - - - 0 0 0 0 0 0 0 0 0 0 0 0 0 0 0 0 0 0 6, - - 7, - - |",
    "1 - - - - - - - - - - - - - - - - - - - - - - - 2 - - - - - - - - - - - - - - - - - - - - - - - | 3 - - - - - - - - - - - - - - - - - - - - - - - - - - - - - - - - - - - - - - - - - - - - - - - | |",
    "0 0 0 0 0 0 1 - - 7, - - 1 - - - - - 2 - - 1 - - 1 - - 5, - - - - - - - - 0 0 0 0 0 0 0 0 0 0 0 0 | 1 - - - - - 1 - - 1 - - 1 - - 2 - - 3 - - 3 - - 3 - - - - - - - - - - - 0 0 0 0 0 0 0 0 0 0 0 0 |",
    "0 0 0 0 0 0 1 - - 7, - - 1 - - - - - 2 - - 1 - - 1 - - 5, - - - - - - - - 0 0 0 0 0 0 0 0 0 0 0 0 | 4 - - - - - 4 - - 3 - - 3 - - 1 - - 2 - - 2 - - 2 - - - - - - - - - - - 0 0 0 0 0 0 0 0 0 0 0 0 | 0 0 0 0 0 0 1 - - 7, - - 1 - - - - - 2 - - 1 - - 1 - - 5, - - - - - - - - 0 0 0 0 0 0 0 0 0 0 0 0 | 1 - - - - - 1 - - 1 - - 1 - - 2 - - 3 - - 3 - - 3 - - - - - - - - - - - 0 0 0 0 0 0 0 0 0 0 0 0 |",
    "4 - - - - - - - - 3 - - 3 - - - - - 1 - - - - - 1 - - - - - - - - - - - 7, - - - - - 1 - - - - - | 1 - - - - - - - - - - - - - - - - - - - - - - - 0 0 0 0 0 0 0 0 0 0 0 0 0 0 0 0 0 0 0 0 0 0 0 0 |",
    "0 0 0 0 0 0 1 - - 7, - - 1 - - - - - 2 - - 1 - - 1 - - - - - - - - 5 - - 5 - - - - - - - - 5 - - | 4 - - - - - 3 - - 4 - - 4 - - 5 - - - - - 5 - - 5 - - 4 - - 3 - - - - - 3 - - - - - - - - - - - |",
    "0 0 0 0 0 0 1 - - 7, - - 1 - - - - - 6 - - - - - 5 - - - - - - - - 2 - - 2 - - - - - 1 - - - - - | 1 - - - - - - - - - - - - - - - - - - - - - - - - - - - - - - - - - - - 0 0 0 0 0 0 0 0 0 0 0 0 | 4 - - - - - - - - 3 - - 3 - - - - - 1 - - - - - 1 - - - - - - - - - - - 2 - - - - - - - - - - - | 3 - - - - - 3 - - - - - 3 - - - - - 5 - - - - - 4 - - - - - - - - - - - 3 - - - - - 2 - - 1 - - |",
    "2 - - - - - 2 - - - - - 2 - - - - - 4 - - - - - 3 - - 4 - - 3 - - - - - 2 - - - - - - - - - - - | 1 - - - - - 7, - - 1 - - 1 - - - - - 2 - - 3 - - 3 - - - - - 2 - - 1 - - 1 - - 7, - - 7, - - 6, - - | 7, - - 6, - - 0 0 0 0 0 0 6, - - - - - 1 - - - - - 1 - - - - - - - - 2 - - 2 - - - - - - - - - - - | 1 - - - - - 1 - - - - - 1 - - - - - 3 - - - - - 2 - - - - - - - - 1 - - 1 - - - - - - - - - - - |",
    "7, - - - - - 7, - - - - - 7, - - - - - 2 - - - - - 1 - - - - - 1 - - 7, - - 7, - - - - - - - - - - - | 6, - - - - - 6, - - 6, - - 6, - - - - - 7, - - - - - 1 - - - - - 7, - - 6, - - 6, - - 5, - - 5, - - 6, - - | 6, - - - - - 0 0 0 0 0 0 6 - - - - - 7 - - 1' - - 1' - - - - - - - - 2' - - 2' - - - - - - - - - - - | 5 - - - - - 5 - - - - - 5 - - - - - 7 - - - - - 6 - - - - - - - - - - - 5 - - - - - - - - - - - |",
    "5 - - - - - 5 - - - - - 5 - - - - - 5 - - - - - #5 - - - - - 5 - - - - - 6 - - - - - 7 - - - - - | 6 - - - - - 6 - - 6 - - 6 - - - - - 7 - - - - - 1' - - - - - 7 - - 6 - - 6 - - 5 - - 5 - - 6 - - | 6 - - - - - - - - - - - - - - - - - - - - - - - - - - - - - - - - - - - 0 0 0 0 0 0 0 0 0 0 0 0 | 0 0 0 0 0 0 0 0 0 0 0 0 6 - - - 7 - - - 1' - - - 2' - - - - - - - - - - - - - - - - - 3' - - - - - |",
    "3' - - - - - - - - - - - - - - - - - - - - - - - - - - - - - - - - - - - - - - - - - - - - - - - | 5' - - - - - - - - - - - - - - - - - - - - - - - 0 0 0 6' - - - - - - - - 2' - - 1' - - - - - 2' 1' 6 | 6 - - 1' - - - - - - - - 1' - - - - - - - - - - - - - - - - - - - - - - - - - - - - - - - - - - - |",
    "|",
    "0 0 0 0 0 0 0 0 0 0 0 0 0 0 0 0 0 0 0 0 0 0 0 0 0 0 0 0 0 0 0 0 0 0 0 0 0 0 0 0 0 0 6 - - 7 - - | 1' - - - - - - - - - - - - - - - - - - - - - - - - - - - - - - - - - - - 1' - - - - - - - - - - - |",
    "7 - - 6 - - 5 - - 5 - - 5 - - - - - - - - 0 0 0 2' - - - - - - - - 1' - - 1' - - 7 - - - - - 6 - - | 6 - - 5 - - - - - - - - - - - 6 - - - - - - - - 6 - - - - - - - - - - - 6 - - - - - - - - 6 - - 6 - - 6 - - 5 - - - - - | 5 - - - - - - - - - - - 0 0 0 0 0 0 0 0 0 3' - - 3' - - 5' - - - - - 5' - - 5' - - 5' - - - - - 2' - - | |",
    "2' - - 1' - - - - - - - - 1' - - - - - - - - - - - - - - - - - - - - - - - - - - - - - - - - - - - | 7 - - - - - 6 - - 5 - - 5 - - - - - - - - - - - 0 0 0 0 0 0 0 0 0 0 0 0 6 - - - - - - - - - - - | 6 - - - - - - - - - - - - - - - - - - - - - - - - - - - - - - - - - - - - - - - - - - - - - - - | 6 - - - - - - - - - - - - - - - - - - - - - - - 0 0 0 0 0 0 0 0 0 0 0 0 0 0 0 0 0 0 0 0 0 0 0 0 | | |"
  ]
}
